README.rst
setup.py
limit/__init__.py
limit/limit.py
limit.egg-info/PKG-INFO
limit.egg-info/SOURCES.txt
limit.egg-info/dependency_links.txt
limit.egg-info/top_level.txt