Metadata-Version: 1.0
Name: limit
Version: 0.2.3
Summary: Decorator that limits the calling rate of a function
Home-page: http://github.com/enricobacis/limit
Author: Enrico Bacis
Author-email: enrico.bacis@gmail.com
License: MIT
Keywords: rate ratelimit ratelimiter limit limiting api function
Platform: UNKNOWN
